quickremember/__init__.py
quickremember/consts.py
quickremember/forget.py
quickremember/remember.py
quickremember-0.1.0rc1.dist-info/LICENSE
quickremember-0.1.0rc1.dist-info/METADATA
quickremember-0.1.0rc1.dist-info/WHEEL
quickremember-0.1.0rc1.dist-info/entry_points.txt
quickremember-0.1.0rc1.dist-info/top_level.txt
quickremember-0.1.0rc1.dist-info/RECORD
