Metadata-Version: 2.1
Name: quickremember
Version: 0.1.0rc1
Summary: Simple CLI application to remember simple things.
Author-email: Trevin Jones <trevindjones@gmail.com>
License: MIT
Keywords: notes,cli,linux
Classifier: Programming Language :: Python :: 3
Requires-Python: >=3.7
License-File: LICENSE
Requires-Dist: thefuzz
